secretsmith/__init__.py
secretsmith/vault/__init__.py
secretsmith/vault/client.py
secretsmith/vault/config.py
secretsmith/vault/secrets.py
secretsmith/vault/utils.py
secretsmith-0.1.0.dist-info/METADATA
secretsmith-0.1.0.dist-info/WHEEL
secretsmith-0.1.0.dist-info/top_level.txt
secretsmith-0.1.0.dist-info/RECORD
