Metadata-Version: 2.4
Name: secretsmith
Version: 0.1.0
Summary: Connect to Vault with a configuration file
Home-page: https://devcentral.nasqueron.org/source/reports/
Author: Sébastien Santoro
Author-email: dereckson@espace-win.org
License: BSD-2-Clause
Project-URL: Bug Tracker, https://devcentral.nasqueron.org/
Project-URL: Documentation, https://docs.nasqueron.org/secretsmith/
Project-URL: Source Code, https://devcentral.nasqueron.org/source/reports/browse/main/tools/secretsmith/
Classifier: Programming Language :: Python :: 3
Classifier: Operating System :: OS Independent
Classifier: Intended Audience :: Developers
Classifier: Topic :: Security
Requires-Python: >=3.6
Requires-Dist: PyYAML<7.0,>=6.0
Requires-Dist: hvac<3.0,>=2.3
